{
  "author": "FQwPfMiT",
  "id": "1afdgvMON",
  "title": "БЕРЕЖАНИ",
  "link": "metrs_poem.php?poem=15331",
  "html": "\n<h4></h4>\n\n<a href=\"/metrs.php?id=259&amp;type=tvorch\" class=\"redhr1\">Творчість</a> |\n<a href=\"/metrs.php?id=259&amp;type=biogr\" class=\"redhr1\">Біографія</a> |\n<a href=\"/metrs.php?id=259&amp;type=critiques\" class=\"redhr1\">Критика</a>\n\n<h4>БЕРЕЖАНИ</h4>\n<!--<div style=\"float:right;margin-left: 10px\">\n\t<script async src=\"//pagead2.googlesyndication.com/pagead/js/adsbygoogle.js\"></script>\n\n\t<ins class=\"adsbygoogle\"\n\t\t style=\"display:inline-block;width:250px;height:400px\"\n\t\t data-ad-client=\"ca-pub-5357335372099528\"\n\t\t data-ad-slot=\"7581761695\"></ins>\n\t<script>\n\t(adsbygoogle = window.adsbygoogle || []).push({});\n\t</script>\n</div>-->\n\nПриїхав &nbsp;знов &nbsp;через &nbsp;багато &nbsp;літ<br>\nВ &nbsp;те &nbsp;місто... &nbsp;в &nbsp;це &nbsp;містечко &nbsp;- &nbsp;помаліло:<br>\nПрименшив &nbsp;так &nbsp;його &nbsp;незмірний &nbsp;світ.<br>\nІ &nbsp;в &nbsp;пам'яті &nbsp;далеке &nbsp;забіліло.<br>\n<br>\nДесь &nbsp;там &nbsp;великі &nbsp;купчаться &nbsp;сніги,<br>\nТече &nbsp;ріка, &nbsp;аж &nbsp;страх &nbsp;бере &nbsp;- &nbsp;глибока,<br>\nВстають &nbsp;горби, &nbsp;як &nbsp;гори &nbsp;крутобокі,<br>\nІ &nbsp;в &nbsp;хащах &nbsp;непролазних &nbsp;береги...<br>\n<br>\nГай-гай, &nbsp;немов &nbsp;крізь &nbsp;лінзи &nbsp;навпаки,<br>\nВже &nbsp;зменшеним, &nbsp;непоказним &nbsp;постало,<br>\nНемов &nbsp;дядьки, &nbsp;що &nbsp;нас &nbsp;на &nbsp;руки &nbsp;брали &nbsp;-<br>\nТепер &nbsp;похилі, &nbsp;немічні &nbsp;дідки.<br>\n<br>\nІ &nbsp;річка &nbsp;поміліла, &nbsp;і &nbsp;сніги,<br>\nБа &nbsp;- &nbsp;навіть &nbsp;сонце &nbsp;не &nbsp;таке &nbsp;яскраве!..<br>\nЛиш &nbsp;здалека &nbsp;привабним, &nbsp;дорогим<br>\nЗрина &nbsp;у &nbsp;світ &nbsp;дитячої &nbsp;уяви.\n\n\n<br><br>\n"
}