{
  "author": "8k3BQM0NT",
  "id": "3oyKWtWre",
  "title": "РУНО",
  "link": "metrs_poem.php?poem=16122",
  "html": "\n<h4></h4>\n\n<a href=\"/metrs.php?id=140&amp;type=tvorch\" class=\"redhr1\">Творчість</a> |\n<a href=\"/metrs.php?id=140&amp;type=biogr\" class=\"redhr1\">Біографія</a> |\n<a href=\"/metrs.php?id=140&amp;type=critiques\" class=\"redhr1\">Критика</a>\n\n<h4>РУНО</h4>\n<!--<div style=\"float:right;margin-left: 10px\">\n\t<script async src=\"//pagead2.googlesyndication.com/pagead/js/adsbygoogle.js\"></script>\n\n\t<ins class=\"adsbygoogle\"\n\t\t style=\"display:inline-block;width:250px;height:400px\"\n\t\t data-ad-client=\"ca-pub-5357335372099528\"\n\t\t data-ad-slot=\"7581761695\"></ins>\n\t<script>\n\t(adsbygoogle = window.adsbygoogle || []).push({});\n\t</script>\n</div>-->\n\nПоїдемо &nbsp;удвоє &nbsp;по &nbsp;закляте &nbsp;руно. &nbsp;<br>\nЗ &nbsp;долоні &nbsp;вітру, &nbsp;що &nbsp;прощався &nbsp;з &nbsp;нами, &nbsp;грудка &nbsp;<br>\nпогаслої &nbsp;зорі &nbsp;упала, &nbsp;мов &nbsp;дарунок. &nbsp;<br>\nВперед! &nbsp;Сім &nbsp;миль &nbsp;кохання &nbsp;і &nbsp;остання &nbsp;— &nbsp;смутку. &nbsp;<br>\n<br>\nВ &nbsp;завії &nbsp;образів &nbsp;поезія &nbsp;і &nbsp;буря. &nbsp;<br>\nДороги &nbsp;стрічка &nbsp;зв’язана &nbsp;у &nbsp;сонця &nbsp;вузол. &nbsp;<br>\nКлонюсь &nbsp;тобі, &nbsp;о &nbsp;пані &nbsp;кучерявих &nbsp;куряв, &nbsp;<br>\nщо &nbsp;дзвониш &nbsp;диском &nbsp;літ, &nbsp;струнка &nbsp;епічна &nbsp;музо! &nbsp;<br>\n<br>\nДва &nbsp;коні &nbsp;з &nbsp;снігу &nbsp;й &nbsp;піни &nbsp;й &nbsp;дно &nbsp;кохання &nbsp;темне, &nbsp;<br>\nмоє &nbsp;життя &nbsp;взяла &nbsp;ти &nbsp;в &nbsp;пальці, &nbsp;мов &nbsp;балончик, &nbsp;<br>\nі &nbsp;аж &nbsp;на &nbsp;п’ятій &nbsp;милі &nbsp;спочиватимемо &nbsp;<br>\nна &nbsp;лопуховім &nbsp;листі &nbsp;молодого &nbsp;сонця. &nbsp;<br>\n<br>\nЛілеї &nbsp;з &nbsp;молока &nbsp;і &nbsp;співу &nbsp;над &nbsp;проваллям, &nbsp;<br>\nде &nbsp;кубляться &nbsp;й &nbsp;булькочуть &nbsp;сонні &nbsp;трясовини. &nbsp;<br>\nОсь &nbsp;восьма &nbsp;миля &nbsp;смутку &nbsp;і &nbsp;уста, &nbsp;що &nbsp;палять &nbsp;<br>\nхмільніше &nbsp;від &nbsp;зорі &nbsp;й &nbsp;коротше &nbsp;від &nbsp;хвилини. &nbsp;<br>\n<br>\n<br><br><em>8 січня 1936. </em>\n\n\n<br><br>\n"
}