{
  "author": "NXNex7lH",
  "id": "41QIO_lz",
  "title": "КРАСНА ПЛОЩА",
  "link": "metrs_poem.php?poem=14294",
  "html": "\n<h4></h4>\n\n<a href=\"/metrs.php?id=820&amp;type=tvorch\" class=\"redhr1\">Творчість</a> |\n<a href=\"/metrs.php?id=820&amp;type=biogr\" class=\"redhr1\">Біографія</a> |\n<a href=\"/metrs.php?id=820&amp;type=critiques\" class=\"redhr1\">Критика</a>\n\n<h4>КРАСНА ПЛОЩА</h4>\n<!--<div style=\"float:right;margin-left: 10px\">\n\t<script async src=\"//pagead2.googlesyndication.com/pagead/js/adsbygoogle.js\"></script>\n\n\t<ins class=\"adsbygoogle\"\n\t\t style=\"display:inline-block;width:250px;height:400px\"\n\t\t data-ad-client=\"ca-pub-5357335372099528\"\n\t\t data-ad-slot=\"7581761695\"></ins>\n\t<script>\n\t(adsbygoogle = window.adsbygoogle || []).push({});\n\t</script>\n</div>-->\n\nВ &nbsp;Москві &nbsp;по &nbsp;Красній &nbsp;площі &nbsp;я &nbsp;іду.<br>\nКуранти &nbsp;б'ють,<br>\nСніжок &nbsp;лапатий &nbsp;пада...<br>\nКремлівську &nbsp;зірку &nbsp;бачу &nbsp;молоду<br>\nІ &nbsp;серце &nbsp;грає &nbsp;трепетно &nbsp;і &nbsp;радо...<br>\n<br>\nСіяє &nbsp;зірка &nbsp;на &nbsp;усі &nbsp;світи,<br>\nМов &nbsp;світла &nbsp;мрія,<br>\nМов &nbsp;надій &nbsp;вітрила...<br>\nКомуністична &nbsp;партіє, &nbsp;це &nbsp;ти<br>\nЦю &nbsp;зірку &nbsp;волі &nbsp;для &nbsp;людей &nbsp;відкрила!<br>\n<br>\nЦе &nbsp;Ленін &nbsp;засвітив &nbsp;нам &nbsp;цю &nbsp;зорю,<br>\nЦе &nbsp;Партія &nbsp;несе &nbsp;її &nbsp;по &nbsp;світу...<br>\nЯ &nbsp;- &nbsp;комуніст,<br>\nЯ &nbsp;гордо &nbsp;говорю:<br>\n- &nbsp;Нікому &nbsp;зірку &nbsp;цю &nbsp;не &nbsp;погасити!<br><br><em>Москва, 1954</em>\n\n\n<br><br>\n"
}