{
  "author": "gAr8azM7j",
  "id": "6Twk5YCSA",
  "title": "МИТЬ",
  "link": "/metrs_poem.php?poem=16236",
  "html": "\n<h4></h4>\n\n<a href=\"/metrs.php?id=151&amp;type=tvorch\" class=\"redhr1\">Творчість</a> |\n<a href=\"/metrs.php?id=151&amp;type=biogr\" class=\"redhr1\">Біографія</a> |\n<a href=\"/metrs.php?id=151&amp;type=critiques\" class=\"redhr1\">Критика</a>\n\n<h4>МИТЬ</h4>\n<!--<div style=\"float:right;margin-left: 10px\">\n\t<script async src=\"//pagead2.googlesyndication.com/pagead/js/adsbygoogle.js\"></script>\n\n\t<ins class=\"adsbygoogle\"\n\t\t style=\"display:inline-block;width:250px;height:400px\"\n\t\t data-ad-client=\"ca-pub-5357335372099528\"\n\t\t data-ad-slot=\"7581761695\"></ins>\n\t<script>\n\t(adsbygoogle = window.adsbygoogle || []).push({});\n\t</script>\n</div>-->\n\nСпинись. &nbsp;Молитву &nbsp;тиху &nbsp;прокажи, &nbsp;<br>\nЙ &nbsp;замри, &nbsp;на &nbsp;мить &nbsp;замри &nbsp;в &nbsp;очаруванні. &nbsp;<br>\nКрізь &nbsp;ясенів &nbsp;осінні &nbsp;вітражі &nbsp;<br>\nСтрумують &nbsp;промені &nbsp;золототкані, &nbsp;<br>\n<br>\nАж &nbsp;листя &nbsp;мов &nbsp;дзвенить &nbsp;на &nbsp;ясенах &nbsp;<br>\nДзвінкіше, &nbsp;ніж &nbsp;кришталь. &nbsp;Й &nbsp;цієї &nbsp;ж &nbsp;миті &nbsp;<br>\nОт &nbsp;наяву, &nbsp;а &nbsp;не &nbsp;в &nbsp;забутих &nbsp;снах &nbsp;<br>\nВиводить &nbsp;голуб &nbsp;віражі &nbsp;в &nbsp;зеніті. &nbsp;<br>\n<br>\nПрирученого &nbsp;птаха &nbsp;тихий &nbsp;лет, &nbsp;<br>\nІ &nbsp;сонцепад, &nbsp;і &nbsp;дзенькіт &nbsp;листя &nbsp;мирний, &nbsp;— &nbsp;<br>\nЦе &nbsp;все &nbsp;єдиний &nbsp;створює &nbsp;квартет &nbsp;<br>\nІз &nbsp;миттю &nbsp;та &nbsp;із &nbsp;вічністю &nbsp;співмірний. &nbsp;<br>\n<br>\n\n\n\n<br><br>\n"
}