{
  "author": "NXNex7lH",
  "id": "ckLzk17BN",
  "title": "МИКОЛІ НАГНИБІДІ",
  "link": "metrs_poem.php?poem=14351",
  "html": "\n<h4></h4>\n\n<a href=\"/metrs.php?id=820&amp;type=tvorch\" class=\"redhr1\">Творчість</a> |\n<a href=\"/metrs.php?id=820&amp;type=biogr\" class=\"redhr1\">Біографія</a> |\n<a href=\"/metrs.php?id=820&amp;type=critiques\" class=\"redhr1\">Критика</a>\n\n<h4>МИКОЛІ НАГНИБІДІ</h4>\n<!--<div style=\"float:right;margin-left: 10px\">\n\t<script async src=\"//pagead2.googlesyndication.com/pagead/js/adsbygoogle.js\"></script>\n\n\t<ins class=\"adsbygoogle\"\n\t\t style=\"display:inline-block;width:250px;height:400px\"\n\t\t data-ad-client=\"ca-pub-5357335372099528\"\n\t\t data-ad-slot=\"7581761695\"></ins>\n\t<script>\n\t(adsbygoogle = window.adsbygoogle || []).push({});\n\t</script>\n</div>-->\n\nЯ &nbsp;згадую &nbsp;далекі &nbsp;наші &nbsp;весни &nbsp;-<br>\nТридцяті &nbsp;роки,<br>\nЮнь &nbsp;твою &nbsp;й &nbsp;мою...<br>\nЗгадай &nbsp;і &nbsp;ти &nbsp;- &nbsp;і &nbsp;в &nbsp;пам'яті &nbsp;воскресне<br>\nі &nbsp;ХаПеЗе, &nbsp;і &nbsp;солов'ї &nbsp;в &nbsp;гаю.<br>\nТи &nbsp;був &nbsp;тоді &nbsp;робітником. &nbsp;У &nbsp;шумі<br>\nЗаводу &nbsp;гартувався &nbsp;зліт &nbsp;думок...<br>\nХодили &nbsp;у &nbsp;юнгштурмівськім &nbsp;костюмі,<br>\nНа &nbsp;грудях &nbsp;- &nbsp;комсомольський &nbsp;був &nbsp;значок!<br>\nО &nbsp;незабутні &nbsp;комсомольські &nbsp;роки!<br>\nСуботники...<br>\nМи &nbsp;зводили &nbsp;Держпром,<br>\nІ &nbsp;Дніпрогес, &nbsp;і &nbsp;шахт &nbsp;копри &nbsp;високі...<br>\nУсі &nbsp;ми &nbsp;йшли &nbsp;з &nbsp;піднесеним &nbsp;чолом!<br>\nМи &nbsp;- &nbsp;комсомольське &nbsp;наше &nbsp;покоління,<br>\nЕнтузіасти &nbsp;п'ятирічок! &nbsp;Ми,<br>\nХто &nbsp;за &nbsp;наказом &nbsp;власного &nbsp;сумління<br>\nБудов &nbsp;кресали &nbsp;блискавки &nbsp;й &nbsp;громи,<br>\nЗаклавши &nbsp;Комсомольських &nbsp;свій &nbsp;на &nbsp;Амурі,<br>\nЦехи &nbsp;Магнітки &nbsp;-<br>\nЗгине &nbsp;хай &nbsp;старе!<br>\nЯк &nbsp;шкірились &nbsp;на &nbsp;нас &nbsp;щури &nbsp;похмурі &nbsp;-<br>\nПілсудський, &nbsp;Чемберлен, &nbsp;Пуанкаре!..<br>\nГроми &nbsp;будов &nbsp;гули &nbsp;по &nbsp;всьому &nbsp;світу,<br>\nНагадуючи &nbsp;їм &nbsp;\"Авроры\" &nbsp;грім,<br>\nБ'ючи &nbsp;давно &nbsp;вже &nbsp;їхню &nbsp;карту &nbsp;биту...<br>\nТой &nbsp;грім &nbsp;-<br>\nЦе &nbsp;гімн &nbsp;ровесникам &nbsp;моїм!<br>\nТой &nbsp;грім &nbsp;- &nbsp;салюти &nbsp;ленінським &nbsp;знаменам,<br>\nЩо &nbsp;день &nbsp;несуть &nbsp;в &nbsp;капіталізму &nbsp;ніч...<br>\nВ &nbsp;костюмі &nbsp;у &nbsp;юнгштурмівськім &nbsp;зеленім<br>\nІшли, &nbsp;куди &nbsp;показував &nbsp;Ілліч!<br>\nБуремні &nbsp;ви, &nbsp;життя &nbsp;широкі &nbsp;ріки!<br>\nСолдатами &nbsp;були &nbsp;ми &nbsp;- &nbsp;я &nbsp;і &nbsp;ти,<br>\nСолдатами &nbsp;ми &nbsp;будемо &nbsp;довіку,<br>\nЯкі &nbsp;б &nbsp;нас &nbsp;не &nbsp;покликали &nbsp;фронти!<br>\nХоч &nbsp;сивина &nbsp;й &nbsp;припорошила &nbsp;літ, &nbsp;-<br>\nМи &nbsp;й &nbsp;досі &nbsp;комсомольці! &nbsp;Не &nbsp;холоне<br>\nВогонь &nbsp;сердець<br>\nДуші &nbsp;не &nbsp;в'яне &nbsp;цвіт!<br>\nДушею &nbsp;ми &nbsp;й &nbsp;сьогодні &nbsp;в &nbsp;комсомолі,<br>\nЯк &nbsp;в &nbsp;ті &nbsp;юнацькі &nbsp;роки, &nbsp;як &nbsp;тоді.<br>\nІ &nbsp;ми &nbsp;не &nbsp;постаріємо &nbsp;ніколи,<br>\nБо &nbsp;мрії &nbsp;наші,<br>\nСтяги &nbsp;- &nbsp;молоді!<br><br><em>Київ, 1961</em>\n\n\n<br><br>\n"
}