{
  "author": "1BIp2mpC",
  "id": "Cmx_vXcgV",
  "title": "МАЛЬВИ",
  "link": "metrs_poem.php?poem=13503",
  "html": "\n<h4></h4>\n\n<a href=\"/metrs.php?id=65&amp;type=tvorch\" class=\"redhr1\">Творчість</a> |\n<a href=\"/metrs.php?id=65&amp;type=biogr\" class=\"redhr1\">Біографія</a> |\n<a href=\"/metrs.php?id=65&amp;type=critiques\" class=\"redhr1\">Критика</a>\n\n<h4>МАЛЬВИ</h4>\n<!--<div style=\"float:right;margin-left: 10px\">\n\t<script async src=\"//pagead2.googlesyndication.com/pagead/js/adsbygoogle.js\"></script>\n\n\t<ins class=\"adsbygoogle\"\n\t\t style=\"display:inline-block;width:250px;height:400px\"\n\t\t data-ad-client=\"ca-pub-5357335372099528\"\n\t\t data-ad-slot=\"7581761695\"></ins>\n\t<script>\n\t(adsbygoogle = window.adsbygoogle || []).push({});\n\t</script>\n</div>-->\n\nМамо, &nbsp;світяться &nbsp;мальви<br>\nна &nbsp;світанку &nbsp;зими.<br>\nЇх &nbsp;вітри &nbsp;не &nbsp;зламали,<br>\nїх &nbsp;не &nbsp;вбили &nbsp;громи.<br>\n<br>\nНад &nbsp;літами, &nbsp;світами<br>\nя &nbsp;лечу, &nbsp;я &nbsp;іду.<br>\nБачу, &nbsp;мамо: &nbsp;світає<br>\nу &nbsp;холоднім &nbsp;саду.<br>\n<br>\nЗа &nbsp;рожевим &nbsp;туманом<br>\nснить &nbsp;морозами &nbsp;путь.<br>\nТи &nbsp;чекай &nbsp;мене, &nbsp;мамо,<br>\nпоки &nbsp;мальви &nbsp;цвітуть.<br>\n<br>\nТеплих &nbsp;днів &nbsp;ще &nbsp;багато<br>\nнам &nbsp;віщують &nbsp;вони.<br>\nГен &nbsp;за &nbsp;мальвами &nbsp;хата<br>\nвиплива &nbsp;з &nbsp;далини.<br>\n<br>\nПеред &nbsp;мальвою, &nbsp;мамо,<br>\nя &nbsp;повік &nbsp;у &nbsp;боргу.<br>\nМамо, &nbsp;світяться &nbsp;мальви,<br>\nчервоніють &nbsp;засмучені &nbsp;мальви<br>\nна &nbsp;снігу<br>\nта &nbsp;й &nbsp;на &nbsp;білім &nbsp;снігу.\n\n\n<br><br>\n"
}