{
  "author": "S-n3HtBTP",
  "id": "Dl1y3r0TX",
  "title": "КИЇВ",
  "link": "metrs_poem.php?poem=7636",
  "html": "\n<h4></h4>\n\n<a href=\"/metrs.php?id=37&amp;type=tvorch\" class=\"redhr1\">Творчість</a> |\n<a href=\"/metrs.php?id=37&amp;type=biogr\" class=\"redhr1\">Біографія</a> |\n<a href=\"/metrs.php?id=37&amp;type=critiques\" class=\"redhr1\">Критика</a>\n\n<h4>КИЇВ</h4>\n<!--<div style=\"float:right;margin-left: 10px\">\n\t<script async src=\"//pagead2.googlesyndication.com/pagead/js/adsbygoogle.js\"></script>\n\n\t<ins class=\"adsbygoogle\"\n\t\t style=\"display:inline-block;width:250px;height:400px\"\n\t\t data-ad-client=\"ca-pub-5357335372099528\"\n\t\t data-ad-slot=\"7581761695\"></ins>\n\t<script>\n\t(adsbygoogle = window.adsbygoogle || []).push({});\n\t</script>\n</div>-->\n\nНе &nbsp;чути &nbsp;мови &nbsp;рідної &nbsp;в &nbsp;столиці,<br>\nА &nbsp;там, &nbsp;де &nbsp;Лавра &nbsp;золотом &nbsp;сія,<br>\nВиховують &nbsp;дядьки &nbsp;бородолиці<br>\nЦаревного &nbsp;лакея &nbsp;й &nbsp;холуя.<br>\n<br>\nБіля &nbsp;соборів &nbsp;густо, &nbsp;мов &nbsp;терміти,<br>\nРяхтять, &nbsp;біжать &nbsp;бездонні &nbsp;животи,<br>\nІ &nbsp;в'януть &nbsp;наші &nbsp;синьо-жовті &nbsp;квіти<br>\nТам, &nbsp;де &nbsp;вовік &nbsp;належить &nbsp;їм &nbsp;цвісти.<br>\n<br>\nЗбудися, &nbsp;Києве! &nbsp;Орда &nbsp;- &nbsp;в &nbsp;святині!<br>\nМолися, &nbsp;говори, &nbsp;дававй &nbsp;одвіт!<br>\nА &nbsp;ні &nbsp;- &nbsp;то &nbsp;спи. &nbsp;Проснешся &nbsp;в &nbsp;домовині,<br>\nТвойого &nbsp;крику &nbsp;не &nbsp;почує &nbsp;світ!<br><br><em>15.IV.2005</em>\n\n\n<br><br>\n"
}