{
  "author": "_OeN8BnlH",
  "id": "dz4Hx5U9",
  "title": "КОЛИСКОВА",
  "link": "metrs_poem.php?poem=17854",
  "html": "\n<h4></h4>\n\n<a href=\"/metrs.php?id=47&amp;type=tvorch\" class=\"redhr1\">Творчість</a> |\n<a href=\"/metrs.php?id=47&amp;type=biogr\" class=\"redhr1\">Біографія</a> |\n<a href=\"/metrs.php?id=47&amp;type=critiques\" class=\"redhr1\">Критика</a>\n\n<h4>КОЛИСКОВА</h4>\n<!--<div style=\"float:right;margin-left: 10px\">\n\t<script async src=\"//pagead2.googlesyndication.com/pagead/js/adsbygoogle.js\"></script>\n\n\t<ins class=\"adsbygoogle\"\n\t\t style=\"display:inline-block;width:250px;height:400px\"\n\t\t data-ad-client=\"ca-pub-5357335372099528\"\n\t\t data-ad-slot=\"7581761695\"></ins>\n\t<script>\n\t(adsbygoogle = window.adsbygoogle || []).push({});\n\t</script>\n</div>-->\n\nСпить &nbsp;моєї &nbsp;доні &nbsp;рожевий &nbsp;возик, &nbsp;<br>\nзасотаний &nbsp;смарагдовим &nbsp;царством &nbsp;кропу,<br>\nзабризканий &nbsp;зернами &nbsp;сонячної &nbsp;бронзи<br>\nі &nbsp;кропилом &nbsp;дощу &nbsp;покроплнеий.<br>\n<br>\nЗаплутані &nbsp;колеса &nbsp;в &nbsp;куделях &nbsp;бадилля,<br>\nв &nbsp;променях &nbsp;пралісу &nbsp;гички &nbsp;цибулі.<br>\nКурить &nbsp;земля &nbsp;зела &nbsp;озонне &nbsp;кадило<br>\nі &nbsp;сама &nbsp;гудить &nbsp;терпкавим &nbsp;термолом &nbsp;вулію.<br>\n<br>\nСтікають &nbsp;зі &nbsp;стебел &nbsp;вишневі &nbsp;краплі &nbsp;зозульок<br>\nна &nbsp;засотаний &nbsp;кропом &nbsp;рожевий &nbsp;возик.<br>\nБавиться &nbsp;моя &nbsp;доня &nbsp;зі &nbsp;сонцем &nbsp;у &nbsp;жмурки<br>\nі &nbsp;потягається &nbsp;в &nbsp;найсолодшому &nbsp;позіху.<br><br><em>1966.</em>\n\n\n<br><br>\n"
}