{
  "author": "1BIp2mpC",
  "id": "E2X9BAgVe",
  "title": "ВІДПОВІДЬ АНОНІМУ",
  "link": "metrs_poem.php?poem=13378",
  "html": "\n<h4></h4>\n\n<a href=\"/metrs.php?id=65&amp;type=tvorch\" class=\"redhr1\">Творчість</a> |\n<a href=\"/metrs.php?id=65&amp;type=biogr\" class=\"redhr1\">Біографія</a> |\n<a href=\"/metrs.php?id=65&amp;type=critiques\" class=\"redhr1\">Критика</a>\n\n<h4>ВІДПОВІДЬ АНОНІМУ</h4>\n<!--<div style=\"float:right;margin-left: 10px\">\n\t<script async src=\"//pagead2.googlesyndication.com/pagead/js/adsbygoogle.js\"></script>\n\n\t<ins class=\"adsbygoogle\"\n\t\t style=\"display:inline-block;width:250px;height:400px\"\n\t\t data-ad-client=\"ca-pub-5357335372099528\"\n\t\t data-ad-slot=\"7581761695\"></ins>\n\t<script>\n\t(adsbygoogle = window.adsbygoogle || []).push({});\n\t</script>\n</div>-->\n\nВідкрийся, &nbsp;таємничий &nbsp;аноніме,<br>\nвідкинь &nbsp;забрало &nbsp;куцого &nbsp;листа!<br>\nХай &nbsp;кривляться &nbsp;крикливо, &nbsp;а &nbsp;не &nbsp;німо<br>\nчорнилом &nbsp;запечатані &nbsp;вуста.<br>\n<br>\nТопчу &nbsp;ногами &nbsp;тінь &nbsp;твою &nbsp;убогу,<br>\nале &nbsp;в &nbsp;юрбі &nbsp;тебе &nbsp;не &nbsp;впізнаю.<br>\nТи &nbsp;цілишся &nbsp;примружено &nbsp;з-за &nbsp;рогу<br>\nу &nbsp;посмішку &nbsp;беззахисну &nbsp;мою.<br>\n<br>\nТи &nbsp;вимушено &nbsp;тиснеш &nbsp;мені &nbsp;руку,<br>\nі &nbsp;лиш &nbsp;манжетик &nbsp;білий &nbsp;прикрива<br>\nтвою &nbsp;змокрілу &nbsp;руку, &nbsp;мов &nbsp;гадюку,<br>\nщо &nbsp;виповзає &nbsp;з &nbsp;лігва &nbsp;рукава.<br>\n<br>\nЛукавий &nbsp;небораче &nbsp;аноніме,<br>\nтебе &nbsp;ховає &nbsp;темрява &nbsp;густа,<br>\nі &nbsp;корчиться &nbsp;в &nbsp;сухотній &nbsp;анемії<br>\nогризок &nbsp;безіменного &nbsp;листа.<br>\n<br>\nМене &nbsp;зміїним &nbsp;словом &nbsp;не &nbsp;обкрутиш &nbsp;-<br>\nбезповоротно &nbsp;час &nbsp;твій &nbsp;промина.<br>\nТож &nbsp;наливай &nbsp;чорнильної &nbsp;отрути<br>\nі &nbsp;на &nbsp;здоров'я &nbsp;пий &nbsp;собі &nbsp;до &nbsp;дна!\n\n\n<br><br>\n"
}