{
  "author": "M6Ympf83",
  "id": "jc_NX6RTi",
  "title": "ПРИЗНАЧЕННЯ",
  "link": "metrs_poem.php?poem=21251",
  "html": "\n<h4></h4>\n\n<a href=\"/metrs.php?id=1077&amp;type=tvorch\" class=\"redhr1\">Творчість</a> |\n<a href=\"/metrs.php?id=1077&amp;type=biogr\" class=\"redhr1\">Біографія</a> |\n<a href=\"/metrs.php?id=1077&amp;type=critiques\" class=\"redhr1\">Критика</a>\n\n<h4>ПРИЗНАЧЕННЯ</h4>\n<!--<div style=\"float:right;margin-left: 10px\">\n\t<script async src=\"//pagead2.googlesyndication.com/pagead/js/adsbygoogle.js\"></script>\n\n\t<ins class=\"adsbygoogle\"\n\t\t style=\"display:inline-block;width:250px;height:400px\"\n\t\t data-ad-client=\"ca-pub-5357335372099528\"\n\t\t data-ad-slot=\"7581761695\"></ins>\n\t<script>\n\t(adsbygoogle = window.adsbygoogle || []).push({});\n\t</script>\n</div>-->\n\nМожливо, &nbsp;я &nbsp;лиш &nbsp;згущення &nbsp;молекул &nbsp;<br>\nКосмічного &nbsp;проміння &nbsp;й &nbsp;порошин, &nbsp;<br>\nПризначених &nbsp;у &nbsp;подорож &nbsp;далеку, &nbsp;<br>\nЯк &nbsp;паливо &nbsp;для &nbsp;сонячних &nbsp;машин. &nbsp;<br>\n<br>\nЯ &nbsp;всесвіту &nbsp;дрібненька &nbsp;порошинка, &nbsp;<br>\nВ &nbsp;якій &nbsp;заховані &nbsp;призначення &nbsp;й &nbsp;мета &nbsp;<br>\nЯ &nbsp;знаю, &nbsp;як &nbsp;людина &nbsp;смертна &nbsp;й &nbsp;жінка, &nbsp;<br>\nЩо &nbsp;я &nbsp;частина &nbsp;Вічного &nbsp;Життя.<br>\n\n\n\n<br><br>\n"
}