{
  "author": "FQwPfMiT",
  "id": "meB38AxB",
  "title": "МАЛЛАНЮКОВЕ СЛОВО",
  "link": "metrs_poem.php?poem=14983",
  "html": "\n<h4></h4>\n\n<a href=\"/metrs.php?id=259&amp;type=tvorch\" class=\"redhr1\">Творчість</a> |\n<a href=\"/metrs.php?id=259&amp;type=biogr\" class=\"redhr1\">Біографія</a> |\n<a href=\"/metrs.php?id=259&amp;type=critiques\" class=\"redhr1\">Критика</a>\n\n<h4>МАЛЛАНЮКОВЕ СЛОВО</h4>\n<!--<div style=\"float:right;margin-left: 10px\">\n\t<script async src=\"//pagead2.googlesyndication.com/pagead/js/adsbygoogle.js\"></script>\n\n\t<ins class=\"adsbygoogle\"\n\t\t style=\"display:inline-block;width:250px;height:400px\"\n\t\t data-ad-client=\"ca-pub-5357335372099528\"\n\t\t data-ad-slot=\"7581761695\"></ins>\n\t<script>\n\t(adsbygoogle = window.adsbygoogle || []).push({});\n\t</script>\n</div>-->\n\n1<br>\nЩе, &nbsp;кажуть, &nbsp;груша &nbsp;тільки &nbsp;над &nbsp;Синюхою,<br>\nЩе &nbsp;тільки &nbsp;груша &nbsp;тріпотить &nbsp;одна<br>\nЯким &nbsp;вже &nbsp;листям... &nbsp;Вітер &nbsp;інший &nbsp;дмухає,<br>\nХоч &nbsp;будить &nbsp;хвилю &nbsp;- &nbsp;не &nbsp;пробудить &nbsp;дна.<br>\n<br>\nЗаснула &nbsp;пам'ять. &nbsp;Наче &nbsp;листя, &nbsp;люди<br>\nОсипались &nbsp;- &nbsp;хто &nbsp;знав &nbsp;його &nbsp;і &nbsp;чув<br>\nІ &nbsp;все &nbsp;чуже &nbsp;натискує &nbsp;на &nbsp;груди<br>\nЙого &nbsp;землі, &nbsp;що &nbsp;спрагла &nbsp;без &nbsp;дощу,<br>\n<br>\nЖивого &nbsp;- &nbsp;як &nbsp;його &nbsp;зернисте &nbsp;слово,<br>\nЩо &nbsp;висіється &nbsp;в &nbsp;збуждені &nbsp;степи.<br>\n...Щоб &nbsp;жниво &nbsp;тут &nbsp;зросло &nbsp;Маланюкове<br>\nІ &nbsp;заблищали &nbsp;золоті &nbsp;серпи.<br>\n<br>\n2<br>\nМаланюкова &nbsp;чаша &nbsp;-<br>\nвогненна &nbsp;чаша &nbsp;- &nbsp;хто &nbsp;ще &nbsp;таку<br>\nспив &nbsp;полум'яну<br>\nтого &nbsp;бурану<br>\nдуші?..<br>\nХтось &nbsp;скуб<br>\nтоді &nbsp;удома &nbsp;словесне &nbsp;пір'я<br>\nна &nbsp;подушки,<br>\nщоб &nbsp;м'яко &nbsp;слати,<br>\nщоб &nbsp;тепло &nbsp;спати<br>\nу &nbsp;ті &nbsp;роки,<br>\nяк &nbsp;ще &nbsp;останні<br>\nбились &nbsp;повстанці &nbsp;-<br>\nне &nbsp;гинув &nbsp;дух!!<br>\nА &nbsp;муз &nbsp;обранці:<br>\nпоет &nbsp;- &nbsp;стилет &nbsp;мов,<br>\nбрав &nbsp;стилос &nbsp;вранці...<br>\nВідпивши &nbsp;кави, &nbsp;в &nbsp;одах &nbsp;поганці &nbsp;-<br>\nхвалить &nbsp;орду...<br>\nБатьки &nbsp;і &nbsp;внуки,<br>\nнам &nbsp;досі &nbsp;муки<br>\nХриста &nbsp;страшні...<br>\nЖиття &nbsp;ж &nbsp;все &nbsp;- &nbsp;слово,<br>\nМаланюкове &nbsp;-<br>\nмитець &nbsp;в &nbsp;огні!\n\n\n<br><br>\n"
}