{
  "author": "pQMBoyfB",
  "id": "O6ZdzssO",
  "title": "я себе посеред ікони на дерево проміняв...",
  "link": "/metrs_poem.php?poem=20411",
  "html": "\n<h4></h4>\n\n<a href=\"/metrs.php?id=257&amp;type=tvorch\" class=\"redhr1\">Творчість</a> |\n<a href=\"/metrs.php?id=257&amp;type=biogr\" class=\"redhr1\">Біографія</a> |\n<a href=\"/metrs.php?id=257&amp;type=critiques\" class=\"redhr1\">Критика</a>\n\n<h4>я себе посеред ікони на дерево проміняв...</h4>\n<!--<div style=\"float:right;margin-left: 10px\">\n\t<script async src=\"//pagead2.googlesyndication.com/pagead/js/adsbygoogle.js\"></script>\n\n\t<ins class=\"adsbygoogle\"\n\t\t style=\"display:inline-block;width:250px;height:400px\"\n\t\t data-ad-client=\"ca-pub-5357335372099528\"\n\t\t data-ad-slot=\"7581761695\"></ins>\n\t<script>\n\t(adsbygoogle = window.adsbygoogle || []).push({});\n\t</script>\n</div>-->\n\nя &nbsp;себе &nbsp;посеред &nbsp;ікони &nbsp;на &nbsp;дерево &nbsp;проміняв &nbsp;<br>\nі &nbsp;ніч &nbsp;прилипає &nbsp;до &nbsp;горла &nbsp;холодним &nbsp;вологим &nbsp;лезом &nbsp;<br>\nвони &nbsp;справді &nbsp;кожної &nbsp;ночі &nbsp;підбирають &nbsp;мені &nbsp;імена &nbsp;<br>\nі &nbsp;я &nbsp;прикриваю &nbsp;ними &nbsp;свій &nbsp;фіолетовий &nbsp;безум &nbsp;<br>\n<br>\nлегше &nbsp;терпіти &nbsp;муку &nbsp;вона &nbsp;виглядає &nbsp;старшою &nbsp;<br>\nїї &nbsp;благородні &nbsp;стегна &nbsp;прикриті &nbsp;траурним &nbsp;шовком &nbsp;<br>\nя &nbsp;привітаю &nbsp;кожного &nbsp;кому &nbsp;дорога &nbsp;ця &nbsp;лажа &nbsp;<br>\nдоки &nbsp;його &nbsp;в &nbsp;підземному &nbsp;не &nbsp;проковтне &nbsp;тусовка &nbsp;<br>\n<br>\nя &nbsp;можу &nbsp;терпіти &nbsp;кожного &nbsp;третього &nbsp;в &nbsp;цьому &nbsp;світі &nbsp;<br>\nмостити &nbsp;ними &nbsp;дорогу &nbsp;якою &nbsp;прийдуть &nbsp;форелі &nbsp;<br>\nале &nbsp;вони &nbsp;щоранку &nbsp;примушують &nbsp;мене &nbsp;тремтіти &nbsp;<br>\nповернувшись &nbsp;назад &nbsp;у &nbsp;тіло &nbsp;і &nbsp;причинивши &nbsp;двері &nbsp;<br>\n<br>\nта &nbsp;є &nbsp;межа &nbsp;перевтілень &nbsp;старенька &nbsp;самотня &nbsp;земля &nbsp;<br>\nде &nbsp;серед &nbsp;зливи &nbsp;богів &nbsp;забракло &nbsp;єдиного &nbsp;бога &nbsp;<br>\nпостели &nbsp;мені &nbsp;в &nbsp;небі &nbsp;курво &nbsp;я &nbsp;схожий &nbsp;на &nbsp;твоє &nbsp;маля &nbsp;<br>\nмене &nbsp;нема &nbsp;на &nbsp;цім &nbsp;світі &nbsp;мене &nbsp;немає &nbsp;нікого &nbsp;<br>\n<br>\n\n\n\n<br><br>\n"
}