{
  "author": "vKtquhYw",
  "id": "QbStWGAMq",
  "title": "ВИДІННЄ",
  "link": "metrs_poem.php?poem=8730",
  "html": "\n<h4></h4>\n\n<a href=\"/metrs.php?id=103&amp;type=tvorch\" class=\"redhr1\">Творчість</a> |\n<a href=\"/metrs.php?id=103&amp;type=biogr\" class=\"redhr1\">Біографія</a> |\n<a href=\"/metrs.php?id=103&amp;type=critiques\" class=\"redhr1\">Критика</a>\n\n<h4>ВИДІННЄ</h4>\n<!--<div style=\"float:right;margin-left: 10px\">\n\t<script async src=\"//pagead2.googlesyndication.com/pagead/js/adsbygoogle.js\"></script>\n\n\t<ins class=\"adsbygoogle\"\n\t\t style=\"display:inline-block;width:250px;height:400px\"\n\t\t data-ad-client=\"ca-pub-5357335372099528\"\n\t\t data-ad-slot=\"7581761695\"></ins>\n\t<script>\n\t(adsbygoogle = window.adsbygoogle || []).push({});\n\t</script>\n</div>-->\n\n &nbsp; &nbsp; &nbsp; &nbsp; &nbsp;І<br>\nЯ &nbsp;згадую &nbsp;той &nbsp;день &nbsp;і &nbsp;час &nbsp;благословенний,<br>\nЯк &nbsp;дух &nbsp;твій &nbsp;молодий &nbsp;мене &nbsp;з &nbsp;землі &nbsp;підняв<br>\nІ &nbsp;побут &nbsp;хуторний, &nbsp;захмарений, &nbsp;буденний,<br>\nОгнем &nbsp;твоїх &nbsp;очей &nbsp;живущих &nbsp;осіяв.<br>\nЩо &nbsp;та &nbsp;вода &nbsp;в &nbsp;казках &nbsp;живуща &nbsp;і &nbsp;зцілюща?<br>\nЖизнь &nbsp;у &nbsp;тебе &nbsp;в &nbsp;очах, &nbsp;блаженна-невмируща.<br>\n<br>\n &nbsp; &nbsp; &nbsp; &nbsp; &nbsp;ІІ<br>\nТак! &nbsp;Жив &nbsp;я &nbsp;на &nbsp;землі, &nbsp;і &nbsp;ти &nbsp;з &nbsp;небес &nbsp;прийшла,<br>\nНа &nbsp;крилах &nbsp;юності &nbsp;до &nbsp;старощів &nbsp;спустилась;<br>\nТи &nbsp;з &nbsp;раю &nbsp;пахощів &nbsp;з &nbsp;собою &nbsp;принесла.<br>\nІ &nbsp;світом &nbsp;божества &nbsp;душа &nbsp;твоя &nbsp;світилась...<br>\nНі, &nbsp;не &nbsp;мечта &nbsp;свята &nbsp;- &nbsp; &nbsp;небесний &nbsp;херувим;<br>\nБо &nbsp;дух &nbsp;мій &nbsp;загорівсь &nbsp;огнем &nbsp;твоїм &nbsp;живим.<br>\n<br>\n &nbsp; &nbsp; &nbsp; &nbsp; &nbsp;ІІІ<br>\nВоскрес &nbsp;я, &nbsp;і &nbsp;земля &nbsp;тепер &nbsp;мені &nbsp;тісна...<br>\nТи &nbsp;зникла, &nbsp;і &nbsp;тебе &nbsp;не &nbsp;між &nbsp;людьми &nbsp;шукаю.<br>\nПрокинувсь &nbsp;духом &nbsp;я &nbsp;від &nbsp;жизні, &nbsp;як &nbsp;од &nbsp;сна,<br>\nМов &nbsp;олень &nbsp;до &nbsp;води, &nbsp;до &nbsp;божества &nbsp;жадаю.<br>\nВсім &nbsp;серцем &nbsp;вірую &nbsp;в &nbsp;істочник &nbsp;битія,<br>\nДе &nbsp;в &nbsp;бозі &nbsp;зачалась &nbsp;душа &nbsp;свята &nbsp;твоя.\n\n\n<br><br>\n"
}