{
  "author": "FQwPfMiT",
  "id": "QGkHQv-_d",
  "title": "ДОРОГА ДО ПАТРІАРХА",
  "link": "metrs_poem.php?poem=14909",
  "html": "\n<h4></h4>\n\n<a href=\"/metrs.php?id=259&amp;type=tvorch\" class=\"redhr1\">Творчість</a> |\n<a href=\"/metrs.php?id=259&amp;type=biogr\" class=\"redhr1\">Біографія</a> |\n<a href=\"/metrs.php?id=259&amp;type=critiques\" class=\"redhr1\">Критика</a>\n\n<h4>ДОРОГА ДО ПАТРІАРХА</h4>\n<!--<div style=\"float:right;margin-left: 10px\">\n\t<script async src=\"//pagead2.googlesyndication.com/pagead/js/adsbygoogle.js\"></script>\n\n\t<ins class=\"adsbygoogle\"\n\t\t style=\"display:inline-block;width:250px;height:400px\"\n\t\t data-ad-client=\"ca-pub-5357335372099528\"\n\t\t data-ad-slot=\"7581761695\"></ins>\n\t<script>\n\t(adsbygoogle = window.adsbygoogle || []).push({});\n\t</script>\n</div>-->\n\nСело &nbsp;із &nbsp;назвою &nbsp;Заздрість &nbsp;(такі &nbsp;ту &nbsp;родючі &nbsp;землі)<br>\nРодило &nbsp;чорного &nbsp;красеня &nbsp;Йосипа &nbsp;-<br>\nсвого &nbsp;сивого &nbsp;Патріарха...<br>\nІ &nbsp;ця &nbsp;срібна &nbsp;різдвяна &nbsp;дорога &nbsp;(є &nbsp;поруч &nbsp;село &nbsp;Різдвяни)<br>\nстелилась &nbsp;снігами &nbsp;білими,<br>\nзбігала &nbsp;нині &nbsp;до &nbsp;пам'ятника &nbsp;-<br>\nдо &nbsp;вибіленого &nbsp;літами &nbsp;великого &nbsp;кардинала...<br>\nДорога, &nbsp;дорога &nbsp;Сліпого<br>\nбілилася, &nbsp;як &nbsp;полотна &nbsp;- &nbsp;стелилася &nbsp;все &nbsp;світами,<br>\nбілилась &nbsp;літами &nbsp;простелена &nbsp;через &nbsp;усю &nbsp;планету.<br>\nСтелилась &nbsp;Львовом, &nbsp;Києвом &nbsp;і &nbsp;Москвою &nbsp;-<br>\nтяглася &nbsp;аж &nbsp;через &nbsp;Комі, &nbsp;через &nbsp;Колиму &nbsp;і &nbsp;Мордовію,<br>\nчерез &nbsp;суди &nbsp;московські &nbsp;- &nbsp;через &nbsp;табори &nbsp;і &nbsp;тюрми<br>\nдо &nbsp;світлого &nbsp;вічного &nbsp;Риму,<br>\nна &nbsp;Вашингтон, &nbsp;Торонто... &nbsp;І &nbsp;знов &nbsp;через &nbsp;всю &nbsp;планету,<br>\nщоб &nbsp;вибілена, &nbsp;як &nbsp;з &nbsp;льону, &nbsp;верталась &nbsp;на &nbsp;чорні &nbsp;землі &nbsp;-<br>\nДо &nbsp;Львова, &nbsp;до &nbsp;рідної &nbsp;Заздрості &nbsp;в &nbsp;правічних &nbsp;її &nbsp;чорноземах.<br>\nМученицька &nbsp;і &nbsp;довга &nbsp;- &nbsp;дорога &nbsp;Сліпого &nbsp;Йосипа,<br>\nсивого &nbsp;патріарха.<br>\n...Через &nbsp;сніги &nbsp;дорога<br>\nДо &nbsp;Заздрості &nbsp;(але &nbsp;не &nbsp;чорної &nbsp;- &nbsp;білої, &nbsp;під &nbsp;снігами),<br>\nдо &nbsp;хати, &nbsp;і &nbsp;досі &nbsp;збереженої,<br>\nщо &nbsp;через &nbsp;століття &nbsp;діждалась &nbsp;величного &nbsp;красеня &nbsp;- &nbsp;храму<br>\nщо &nbsp;з &nbsp;ним &nbsp;навік &nbsp;обвінчалась &nbsp;на &nbsp;правітцівській &nbsp;садибі.<br>\nВеликий &nbsp;син &nbsp;України &nbsp;вернувся &nbsp;великим &nbsp;храмом<br>\nу &nbsp;золоту, &nbsp;у &nbsp;вимріяну &nbsp;вільну &nbsp;свою &nbsp;Вітчизну,<br>\nде &nbsp;церква &nbsp;його &nbsp;розп'ята &nbsp;(розп'ята &nbsp;самим &nbsp;Сатаною)<br>\nвоскресла, &nbsp;як &nbsp;дивне &nbsp;диво &nbsp;- &nbsp;нам &nbsp;явлене &nbsp;Сином &nbsp;Божим.<br><br><em>Ніч на 08.01.200 р.</em>\n\n\n<br><br>\n"
}