{
  "author": "ZdL3LO3uI",
  "id": "u_Mpi8IK",
  "title": "Притча",
  "link": "/metrs_poem.php?poem=5006",
  "html": "\n<h4></h4>\n\n<a href=\"/metrs.php?id=266&amp;type=tvorch\" class=\"redhr1\">Творчість</a> |\n<a href=\"/metrs.php?id=266&amp;type=biogr\" class=\"redhr1\">Біографія</a> |\n<a href=\"/metrs.php?id=266&amp;type=critiques\" class=\"redhr1\">Критика</a>\n\n<h4>Притча</h4>\n<!--<div style=\"float:right;margin-left: 10px\">\n\t<script async src=\"//pagead2.googlesyndication.com/pagead/js/adsbygoogle.js\"></script>\n\n\t<ins class=\"adsbygoogle\"\n\t\t style=\"display:inline-block;width:250px;height:400px\"\n\t\t data-ad-client=\"ca-pub-5357335372099528\"\n\t\t data-ad-slot=\"7581761695\"></ins>\n\t<script>\n\t(adsbygoogle = window.adsbygoogle || []).push({});\n\t</script>\n</div>-->\n\nбезліч &nbsp;дивних &nbsp;дерев &nbsp;сновигає<br>\nмістом &nbsp;безцільно<br>\nгілля &nbsp;рук &nbsp;із &nbsp;двома &nbsp;листочками &nbsp;долонь<br>\nзаховавши &nbsp;до &nbsp;кишень<br>\n<br>\nкожне &nbsp;має &nbsp;в &nbsp;собі &nbsp;гніздо &nbsp;душі<br>\nяке &nbsp;ніколи &nbsp;не &nbsp;може &nbsp;бути &nbsp;порожнім<br>\n<br>\nа &nbsp;ще &nbsp;як &nbsp;ті &nbsp;дерева &nbsp;були &nbsp;маленькі<br>\nто &nbsp;хтось &nbsp;лихий &nbsp;довідався &nbsp;про &nbsp;гнізда<br>\nі &nbsp;покрав &nbsp;із &nbsp;них &nbsp;пташата &nbsp;болю<br>\nщо &nbsp;й &nbsp;навіть &nbsp;літати &nbsp;тоді &nbsp;ще &nbsp;не &nbsp;вміли<br>\nі &nbsp;відніс &nbsp;ті &nbsp;пташата &nbsp;далеко-далеко<br>\n<br>\nа &nbsp;щоб &nbsp;вони &nbsp;не &nbsp;повернулися &nbsp;як &nbsp;виростуть<br>\nто &nbsp;збудував &nbsp;між &nbsp;ними &nbsp;і &nbsp;деревами<br>\nмісто &nbsp;з &nbsp;кольорових &nbsp;картонних &nbsp;будиночків<br>\nа &nbsp;гнізда &nbsp;дерев &nbsp;що &nbsp;не &nbsp;могли &nbsp;порожніми &nbsp;бути<br>\nнаселив &nbsp;горобцями &nbsp;усі &nbsp;до &nbsp;одного<br>\n\n\n\n<br><br>\n"
}