{
  "author": "BZmHsEdZm",
  "id": "wbxiz2jX",
  "title": "КРИК ЧАЙКИ",
  "link": "/metrs_poem.php?poem=19156",
  "html": "\n<h4></h4>\n\n<a href=\"/metrs.php?id=85&amp;type=tvorch\" class=\"redhr1\">Творчість</a> |\n<a href=\"/metrs.php?id=85&amp;type=biogr\" class=\"redhr1\">Біографія</a> |\n<a href=\"/metrs.php?id=85&amp;type=critiques\" class=\"redhr1\">Критика</a>\n\n<h4>КРИК ЧАЙКИ</h4>\n<!--<div style=\"float:right;margin-left: 10px\">\n\t<script async src=\"//pagead2.googlesyndication.com/pagead/js/adsbygoogle.js\"></script>\n\n\t<ins class=\"adsbygoogle\"\n\t\t style=\"display:inline-block;width:250px;height:400px\"\n\t\t data-ad-client=\"ca-pub-5357335372099528\"\n\t\t data-ad-slot=\"7581761695\"></ins>\n\t<script>\n\t(adsbygoogle = window.adsbygoogle || []).push({});\n\t</script>\n</div>-->\n\nКазала &nbsp;хвилям: &nbsp;<br>\n— &nbsp;Заберіть &nbsp;мене &nbsp;в &nbsp;море! &nbsp;— &nbsp;<br>\nНе &nbsp;зрозуміли &nbsp;<br>\nМоєї &nbsp;мови. &nbsp;<br>\n<br>\nА &nbsp;чайка &nbsp;кричала. &nbsp;<br>\n<br>\nКазала: &nbsp;<br>\n— &nbsp;У &nbsp;мене &nbsp;очі, &nbsp;як &nbsp;вода, &nbsp;<br>\nІ &nbsp;волосся &nbsp;з &nbsp;піни &nbsp;морської… &nbsp;— &nbsp;<br>\nНе &nbsp;розуміли &nbsp;моєї &nbsp;мови. &nbsp;<br>\n<br>\nА &nbsp;чайка &nbsp;кричала. &nbsp;<br>\n<br>\nКазала: &nbsp;<br>\n— &nbsp;Я &nbsp;чужа &nbsp;на &nbsp;землі, &nbsp;<br>\nта &nbsp;й &nbsp;вам &nbsp;чужа. &nbsp;— &nbsp;<br>\nНе &nbsp;розуміли &nbsp;<br>\nМоєї &nbsp;мови. &nbsp;<br>\n<br>\nА &nbsp;чайка &nbsp;кричала. &nbsp;<br>\n<br>\n\n\n\n<br><br>\n"
}