{
  "author": "UdlPpDDk",
  "id": "WY6VpfqMo",
  "title": "\"Чого вода каламутна...\"",
  "link": "metrs_poem.php?poem=473",
  "html": "\n<h4></h4>\n\n<a href=\"/metrs.php?id=92&amp;type=tvorch\" class=\"redhr1\">Творчість</a> |\n<a href=\"/metrs.php?id=92&amp;type=biogr\" class=\"redhr1\">Біографія</a> |\n<a href=\"/metrs.php?id=92&amp;type=critiques\" class=\"redhr1\">Критика</a>\n\n<h4>\"Чого вода каламутна...\"</h4>\n<!--<div style=\"float:right;margin-left: 10px\">\n\t<script async src=\"//pagead2.googlesyndication.com/pagead/js/adsbygoogle.js\"></script>\n\n\t<ins class=\"adsbygoogle\"\n\t\t style=\"display:inline-block;width:250px;height:400px\"\n\t\t data-ad-client=\"ca-pub-5357335372099528\"\n\t\t data-ad-slot=\"7581761695\"></ins>\n\t<script>\n\t(adsbygoogle = window.adsbygoogle || []).push({});\n\t</script>\n</div>-->\n\n*** &nbsp;<br>\n<br>\nЧого &nbsp;вода &nbsp;каламутна &nbsp;— &nbsp;<br>\nЧи &nbsp;не &nbsp;хвиля &nbsp;збила? &nbsp;<br>\nЧого &nbsp;ж &nbsp;я &nbsp;смутна, &nbsp;невесела, &nbsp;<br>\nЧи &nbsp;не &nbsp;мати &nbsp;била? &nbsp;<br>\n<br>\nМене &nbsp;ж &nbsp;мати &nbsp;та &nbsp;й &nbsp;не &nbsp;била &nbsp;— &nbsp;<br>\nСамі &nbsp;сльози &nbsp;ллються: &nbsp;<br>\nВід &nbsp;милого &nbsp;людей &nbsp;нема, &nbsp;<br>\nВід &nbsp;нелюба &nbsp;шлються. &nbsp;<br>\n<br>\nДе &nbsp;ти, &nbsp;милий? &nbsp;Подивися &nbsp;— &nbsp;<br>\nЯку &nbsp;терплю &nbsp;муку; &nbsp;<br>\nПрилинь, &nbsp;прилинь, &nbsp;моє &nbsp;серце, &nbsp;— &nbsp;<br>\nБеруть &nbsp;мою &nbsp;руку. &nbsp;<br>\n<br>\nШвидше, &nbsp;милий, &nbsp;рятуй &nbsp;мене &nbsp;<br>\nВід &nbsp;лютої &nbsp;напасті: &nbsp;<br>\nЯк &nbsp;з &nbsp;нелюбом &nbsp;мені &nbsp;жити, &nbsp;<br>\nТо &nbsp;ліпше &nbsp;пропасти. &nbsp;<br>\n<br>\n*** &nbsp;<br>\n<br>\n\n\n\n<br><br>\n"
}