{
  "author": "9eKE73LA",
  "id": "yskJ1Cs-1",
  "title": "ОБРАЖЕНИЙ ТОРКВЕМАДА",
  "link": "metrs_poem.php?poem=17279",
  "html": "\n<h4></h4>\n\n<a href=\"/metrs.php?id=36&amp;type=tvorch\" class=\"redhr1\">Творчість</a> |\n<a href=\"/metrs.php?id=36&amp;type=biogr\" class=\"redhr1\">Біографія</a> |\n<a href=\"/metrs.php?id=36&amp;type=critiques\" class=\"redhr1\">Критика</a>\n\n<h4>ОБРАЖЕНИЙ ТОРКВЕМАДА</h4>\n<!--<div style=\"float:right;margin-left: 10px\">\n\t<script async src=\"//pagead2.googlesyndication.com/pagead/js/adsbygoogle.js\"></script>\n\n\t<ins class=\"adsbygoogle\"\n\t\t style=\"display:inline-block;width:250px;height:400px\"\n\t\t data-ad-client=\"ca-pub-5357335372099528\"\n\t\t data-ad-slot=\"7581761695\"></ins>\n\t<script>\n\t(adsbygoogle = window.adsbygoogle || []).push({});\n\t</script>\n</div>-->\n\nЯ &nbsp;інквізитор. &nbsp;Ну, &nbsp;і &nbsp;що &nbsp;із &nbsp;того?<br>\nЧи &nbsp;то &nbsp;такі &nbsp;вже &nbsp;злочини &nbsp;страшні?<br>\nЯ &nbsp;не &nbsp;хвалюся. &nbsp;Віку &nbsp;золотого,<br>\nзвичайно &nbsp;ж, &nbsp;не &nbsp;було &nbsp;і &nbsp;при &nbsp;мені.<br>\nНу, &nbsp;катував. &nbsp;Ну, &nbsp;навертав &nbsp;до &nbsp;лона.<br>\nПалив &nbsp;багаття &nbsp;вищі &nbsp;голови.<br>\nЯ &nbsp;їх &nbsp;убив, &nbsp;ну, &nbsp;може, &nbsp;півмільйона.<br>\nАну &nbsp;згадайте &nbsp;– &nbsp;скільки &nbsp;вбили &nbsp;ви?<br>\n<br>\n\n\n\n<br><br>\n"
}